{
  "title": "241e27e6 B8c4 49b0 8f39 4a99c7c40e86",
  "description": "Auto generated metadata for 241e27e6 B8c4 49b0 8f39 4a99c7c40e86",
  "tags": [
    "241e27e6",
    "b8c4",
    "49b0",
    "8f39",
    "4a99c7c40e86"
  ],
  "style": "",
  "rarity": "",
  "category": "card",
  "character": "",
  "color": "",
  "price": "0.00",
  "isActive": true,
  "metadata": {
    "source": "auto-generated",
    "filename": "241e27e6-b8c4-49b0-8f39-4a99c7c40e86.png",
    "syncSourceId": "local-gallery:241e27e6-b8c4-49b0-8f39-4a99c7c40e86.png"
  }
}
