{
  "title": "249d58f7 13ea 4eec B1e4 89242cedad9a",
  "description": "Auto generated metadata for 249d58f7 13ea 4eec B1e4 89242cedad9a",
  "tags": [
    "249d58f7",
    "13ea",
    "4eec",
    "b1e4",
    "89242cedad9a"
  ],
  "style": "",
  "rarity": "",
  "category": "card",
  "character": "",
  "color": "",
  "price": "0.00",
  "isActive": true,
  "metadata": {
    "source": "auto-generated",
    "filename": "249d58f7-13ea-4eec-b1e4-89242cedad9a.png",
    "syncSourceId": "local-gallery:249d58f7-13ea-4eec-b1e4-89242cedad9a.png"
  }
}
